{
  "jsonSchemaSemanticVersion": "1.1.0",
  "imports": [
    {
      "corpusPath": "cdm:/foundations.cdm.json"
    },
    {
      "corpusPath": "Role.cdm.json"
    },
    {
      "corpusPath": "/core/digitalTwin/Site.cdm.json"
    },
    {
      "corpusPath": "Contact.cdm.json"
    }
  ],
  "definitions": [
    {
      "entityName": "RoleSiteContact",
      "extendsEntity": "CdmEntity",
      "hasAttributes": [
        {
          "explanation": "fk Role. to RoleSiteContact.",
          "entity": {
            "entityReference": "Role",
            "appliedTraits": [
              {
                "traitReference": "is.identifiedBy",
                "arguments": [
                  "Role/(resolvedAttributes)/RoleId"
                ]
              }
            ]
          },
          "name": "RoleId",
          "resolutionGuidance": {
            "renameFormat": "{m}",
            "entityByReference": {
              "allowReference": true,
              "foreignKeyAttribute": {
                "name": "RoleId",
                "purpose": "hasA",
                "dataType": "string",
                "description": "Unique identifier either coming from previous system otherwise it needs to be defined",
                "maximumLength": 50
              }
            }
          },
          "purpose": "identifiedBy"
        },
        {
          "explanation": "fk Site. to RoleSiteContact.",
          "entity": {
            "entityReference": "Site",
            "appliedTraits": [
              {
                "traitReference": "is.identifiedBy",
                "arguments": [
                  "Site/(resolvedAttributes)/SiteId"
                ]
              }
            ]
          },
          "name": "SiteId",
          "resolutionGuidance": {
            "renameFormat": "{m}",
            "entityByReference": {
              "allowReference": true,
              "foreignKeyAttribute": {
                "name": "SiteId",
                "purpose": "hasA",
                "dataType": "string",
                "description": "Unique identifier either coming from previous system otherwise it needs to be defined",
                "maximumLength": 50
              }
            }
          },
          "purpose": "identifiedBy"
        },
        {
          "explanation": "fk Contact. to RoleSiteContact.",
          "entity": {
            "entityReference": "Contact",
            "appliedTraits": [
              {
                "traitReference": "is.identifiedBy",
                "arguments": [
                  "Contact/(resolvedAttributes)/ContactId"
                ]
              }
            ]
          },
          "name": "ContactId",
          "resolutionGuidance": {
            "renameFormat": "{m}",
            "entityByReference": {
              "allowReference": true,
              "foreignKeyAttribute": {
                "name": "ContactId",
                "purpose": "hasA",
                "dataType": "string",
                "description": "Unique identifier either coming from previous system otherwise it needs to be defined",
                "maximumLength": 50
              }
            }
          },
          "purpose": "identifiedBy"
        }
      ],
      "displayName": "RoleSiteContact",
      "description": "Linking entity between Role, Site and Organisation"
    }
  ]
}