{
  "jsonSchemaSemanticVersion": "1.1.0",
  "imports": [
    {
      "corpusPath": "cdm:/foundations.cdm.json"
    },
    {
      "corpusPath": "_allImports.cdm.json"
    },
    {
      "corpusPath": "ComponentType.cdm.json"
    }
  ],
  "definitions": [
    {
      "entityName": "WaterMeter",
      "extendsEntity": "CdmEntity",
      "hasAttributes": [
        {
          "name": "WaterMeterId",
          "purpose": "identifiedBy",
          "dataType": "string",
          "description": "Unique identifier either coming from previous system otherwise it needs to be defined",
          "maximumLength": 50
        },
        {
          "explanation": "fk WaterMeter.ComponentTypeId to ComponentType.ComponentTypeId",
          "entity": {
            "entityReference": "ComponentType",
            "appliedTraits": [
              {
                "traitReference": "is.identifiedBy",
                "arguments": [
                  "ComponentType/(resolvedAttributes)/ComponentTypeId"
                ]
              }
            ]
          },
          "name": "ComponentTypeId",
          "resolutionGuidance": {
            "renameFormat": "{m}",
            "entityByReference": {
              "allowReference": true,
              "foreignKeyAttribute": {
                "name": "ComponentTypeId",
                "purpose": "hasA",
                "dataType": "string",
                "description": "Unique identifier either coming from previous system otherwise it needs to be defined",
                "maximumLength": 50
              }
            }
          }
        },
        {
          "name": "Type",
          "purpose": "hasA",
          "dataType": "string",
          "isNullable": true,
          "description": "Water meter type",
          "maximumLength": 50
        },
        {
          "name": "Volume",
          "purpose": "hasA",
          "dataType": "decimal",
          "isNullable": true,
          "description": "Volume in liter",
          "appliedTraits": [
            {
              "traitReference": "is.dataFormat.numeric.shaped",
              "arguments": [
                {
                  "name": "precision",
                  "value": "19"
                },
                {
                  "name": "scale",
                  "value": "6"
                }
              ]
            }
          ]
        },
        {
          "name": "VolumeFlow",
          "purpose": "hasA",
          "dataType": "decimal",
          "isNullable": true,
          "description": "Volume flow",
          "appliedTraits": [
            {
              "traitReference": "is.dataFormat.numeric.shaped",
              "arguments": [
                {
                  "name": "precision",
                  "value": "19"
                },
                {
                  "name": "scale",
                  "value": "6"
                }
              ]
            }
          ]
        },
        {
          "name": "SupplyTemperature",
          "purpose": "hasA",
          "dataType": "decimal",
          "isNullable": true,
          "description": "Supply temperature",
          "appliedTraits": [
            {
              "traitReference": "is.dataFormat.numeric.shaped",
              "arguments": [
                {
                  "name": "precision",
                  "value": "19"
                },
                {
                  "name": "scale",
                  "value": "6"
                }
              ]
            }
          ]
        },
        {
          "name": "Measures",
          "purpose": "hasA",
          "dataType": "string",
          "isNullable": true,
          "description": "Substance that is measured",
          "maximumLength": 50
        }
      ],
      "displayName": "WaterMeter",
      "description": "Information about water meter"
    }
  ]
}